eelifx
