Metadata-Version: 1.1
Name: eelifx
Version: 0.8.2
Summary: Use game state in EmptyEpsilon to control your Lifx globes.
Home-page: https://github.com/cgspeck/eelifx
Author: Chris Speck
Author-email: cgspeck@gmail.com
License: UNKNOWN
Download-URL: https://github.com/cgspeck/eelifx/archive/0.8.2
Keywords: EmptyEpsilon,Lifx
Platform: UNKNOWN
